pyYaOTP/__init__.py
pyYaOTP/main.py
pyYaOTP-0.0.2.dist-info/LICENSE
pyYaOTP-0.0.2.dist-info/METADATA
pyYaOTP-0.0.2.dist-info/WHEEL
pyYaOTP-0.0.2.dist-info/top_level.txt
pyYaOTP-0.0.2.dist-info/RECORD
