Metadata-Version: 2.1
Name: pyYaOTP
Version: 0.0.2
Summary: Python implementation of Yandex OTP based on KeeYaOtp
Home-page: https://github.com/WhiteApfel/pyYaOTP
Author: WhiteApfel
Author-email: white@pfel.ru
License: Mozilla Public License 2.0
Project-URL: Source code, https://github.com/WhiteApfel/pyYaOTP
Project-URL: Write me, https://t.me/whiteapfel
Keywords: =?utf-8?b?eWFuZGV4IG90cCDRj9C90LTQtdC60YEg0LrQu9GO0YcgeWFvdHA=?=
License-File: LICENSE
